{
  "generated_utc": "2026-01-01T09:41:43.402Z",
  "itemset_hash": "b54e5233db44b4e5",
  "count": 69,
  "items": [
    {
      "title": "What To Do About A Problem Like Dianne Feinstein?",
      "url": "https://fivethirtyeight.com/videos/what-to-do-about-a-problem-like-dianne-feinstein",
      "source": "FiveThirtyEight — Nate Silver",
      "published_utc": "2026-01-01T09:38:45.957Z",
      "effects": {
        "lightsaber": false,
        "glitch": false,
        "reasons": []
      },
      "category": "General",
      "region": "World"
    },
    {
      "title": "Politics Podcast",
      "url": "https://fivethirtyeight.com/tag/politics-podcast",
      "source": "FiveThirtyEight — Nate Silver",
      "published_utc": "2026-01-01T09:38:45.957Z",
      "effects": {
        "lightsaber": false,
        "glitch": false,
        "reasons": []
      },
      "category": "General",
      "region": "World"
    },
    {
      "title": "‘Ne Zha 2,’ ‘Zootopia 2’ Lead China Box Office Past $7.4 Billion in 2025",
      "url": "https://variety.com/2026/film/box-office/ne-zha-2-zootopia-2-2025-china-box-office-7-4-billion-1236621734",
      "source": "Film",
      "published_utc": "2026-01-01T09:18:39.000Z",
      "effects": {
        "lightsaber": false,
        "glitch": false,
        "reasons": []
      },
      "category": "General",
      "region": "World"
    },
    {
      "title": "How Our Presidential Endorsement Tracker Works",
      "url": "https://fivethirtyeight.com/methodology/how-our-presidential-endorsement-tracker-works",
      "source": "FiveThirtyEight — Nate Silver",
      "published_utc": "2026-01-01T09:38:45.958Z",
      "effects": {
        "lightsaber": false,
        "glitch": false,
        "reasons": []
      },
      "category": "General",
      "region": "World"
    },
    {
      "title": "Do You Buy That … Last Week’s Election In Wisconsin Was The Most Important Election Of 2023?",
      "url": "https://fivethirtyeight.com/videos/do-you-buy-that-last-weeks-election-in-wisconsin-was-the-most-important-election-of-2023",
      "source": "FiveThirtyEight — Nate Silver",
      "published_utc": "2026-01-01T09:38:45.958Z",
      "effects": {
        "lightsaber": false,
        "glitch": false,
        "reasons": []
      },
      "category": "General",
      "region": "World"
    },
    {
      "title": "Iran security force member killed during protests, official says",
      "url": "https://www.bbc.com/news/articles/c2d7g8krj2po?at_campaign=rss&at_medium=RSS",
      "source": "BBC News",
      "published_utc": "2026-01-01T09:11:24.000Z",
      "effects": {
        "lightsaber": false,
        "glitch": true,
        "reasons": [
          "score≥2.1"
        ],
        "style": "breaker"
      },
      "category": "General",
      "region": "World"
    },
    {
      "title": "Republicans Amplified Pro-Gun Control Protesters In Tennessee",
      "url": "https://fivethirtyeight.com/videos/republicans-amplified-pro-gun-control-protesters-in-tennessee",
      "source": "FiveThirtyEight — Nate Silver",
      "published_utc": "2026-01-01T09:38:45.958Z",
      "effects": {
        "lightsaber": false,
        "glitch": false,
        "reasons": []
      },
      "category": "General",
      "region": "World"
    },
    {
      "title": "What’s Next In The Abortion Drug Case",
      "url": "https://fivethirtyeight.com/videos/whats-next-in-the-abortion-drug-case",
      "source": "FiveThirtyEight — Nate Silver",
      "published_utc": "2026-01-01T09:38:45.958Z",
      "effects": {
        "lightsaber": false,
        "glitch": false,
        "reasons": []
      },
      "category": "General",
      "region": "World"
    },
    {
      "title": "10 musicians to watch in 2026",
      "url": "https://www.dazeddigital.com/music/article/69324/1/10-musicians-to-watch-in-2026-sophia-stel-kibo-tso",
      "source": "Dazed",
      "published_utc": "2026-01-01T09:01:00.000Z",
      "effects": {
        "lightsaber": false,
        "glitch": false,
        "reasons": []
      },
      "category": "Culture",
      "region": "World"
    },
    {
      "title": "How Concerned Are Americans About The Pitfalls Of AI?",
      "url": "https://fivethirtyeight.com/videos/how-concerned-are-americans-about-the-pitfalls-of-ai",
      "source": "FiveThirtyEight — Nate Silver",
      "published_utc": "2026-01-01T09:38:45.958Z",
      "effects": {
        "lightsaber": false,
        "glitch": false,
        "reasons": []
      },
      "category": "General",
      "region": "World"
    },
    {
      "title": "Live From New York: Will AI Replace This Podcast?",
      "url": "https://fivethirtyeight.com/videos/live-from-new-york-will-ai-replace-this-podcast",
      "source": "FiveThirtyEight — Nate Silver",
      "published_utc": "2026-01-01T09:38:45.957Z",
      "effects": {
        "lightsaber": false,
        "glitch": false,
        "reasons": []
      },
      "category": "General",
      "region": "World"
    },
    {
      "title": "Ice Spice's Hottest Shots To Kick Off Her 26th Birthday!",
      "url": "https://www.tmz.com/2026/01/01/ice-spice-hot-shots-birthday",
      "source": "TMZ.com",
      "published_utc": "2026-01-01T09:00:42.000Z",
      "effects": {
        "lightsaber": false,
        "glitch": false,
        "reasons": []
      },
      "category": "General",
      "region": "World"
    },
    {
      "title": "Many Canadians feel hopeful about 2026 but sour on actual solutions: poll",
      "url": "https://globalnews.ca/news/11587764/canada-ipsos-poll-2026-year-ahead",
      "source": "globalnews.ca",
      "published_utc": "2026-01-01T09:00:41.000Z",
      "effects": {
        "lightsaber": true,
        "glitch": false,
        "reasons": [
          "score≥2.6"
        ],
        "style": "lightsaber"
      },
      "category": "General",
      "region": "Canada"
    },
    {
      "title": "Congressman Probing Epstein Files Makes New Year's Resolution Targeting Enablers",
      "url": "https://www.tmz.com/2026/01/01/congressman-suhas-subramanyam-probing-epstein-files",
      "source": "TMZ.com",
      "published_utc": "2026-01-01T09:00:37.000Z",
      "effects": {
        "lightsaber": false,
        "glitch": false,
        "reasons": []
      },
      "category": "General",
      "region": "World"
    },
    {
      "title": "Brickbat: Cracked",
      "url": "https://reason.com/2026/01/01/brickbat-cracked-3",
      "source": "Reason.com",
      "published_utc": "2026-01-01T09:00:11.000Z",
      "effects": {
        "lightsaber": false,
        "glitch": false,
        "reasons": []
      },
      "category": "General",
      "region": "World"
    },
    {
      "title": "At least 10 killed in an explosion at Swiss ski resort town",
      "url": "https://www.aljazeera.com/video/newsfeed/2026/1/1/at-least-10-killed-in-an-explosion-at-swiss-ski-resort-town?traffic_source=rss",
      "source": "Al Jazeera – Breaking News, World News and Video from Al Jazeera",
      "published_utc": "2026-01-01T09:00:02.000Z",
      "effects": {
        "lightsaber": true,
        "glitch": false,
        "reasons": [
          "score≥2.6",
          "body_count≥3"
        ],
        "style": "breaker"
      },
      "category": "General",
      "region": "World"
    },
    {
      "title": "Menemsha Acquires North American Rights to Coming-of-Age Comedy ‘Ethan Bloom’ (EXCLUSIVE)",
      "url": "https://variety.com/2026/film/global/menemsha-ethan-bloom-1236621149",
      "source": "Film",
      "published_utc": "2026-01-01T08:54:00.000Z",
      "effects": {
        "lightsaber": false,
        "glitch": false,
        "reasons": []
      },
      "category": "General",
      "region": "World"
    },
    {
      "title": "Whip Yourself Into Shape With These Stars Breakin' A Sweat!",
      "url": "https://www.tmz.com/2026/01/01/stars-breaking-sweat-back-into-shape",
      "source": "TMZ.com",
      "published_utc": "2026-01-01T08:45:20.000Z",
      "effects": {
        "lightsaber": false,
        "glitch": false,
        "reasons": []
      },
      "category": "General",
      "region": "World"
    },
    {
      "title": "CBS’ NYE Special ‘Nashville’s Big Bash’ Hit By Tech Issues; Network Briefly Switches To ‘Matlock’ Rerun",
      "url": "https://deadline.com/2026/01/cbs-nye-special-nashvilles-big-bash-tech-issues-matlock-1236659616",
      "source": "Deadline",
      "published_utc": "2026-01-01T08:40:19.000Z",
      "effects": {
        "lightsaber": false,
        "glitch": false,
        "reasons": []
      },
      "category": "Culture",
      "region": "World"
    },
    {
      "title": "Trader bags $1M from ‘abnormal’ BROCCOLI714 memecoin activity on Binance",
      "url": "https://cointelegraph.com/news/trader-1m-profit-binance-market-maker-broccoli714",
      "source": "Cointelegraph.com News",
      "published_utc": "2026-01-01T08:37:00.000Z",
      "effects": {
        "lightsaber": false,
        "glitch": false,
        "reasons": []
      },
      "category": "Business",
      "region": "World"
    },
    {
      "title": "Anthony Joshua released from hospital after Nigeria car crash",
      "url": "https://nypost.com/2026/01/01/sports/anthony-joshua-released-from-hospital-after-nigeria-car-crash",
      "source": "NY Post Sports – Latest News, Scores, Stats & Videos",
      "published_utc": "2026-01-01T08:31:51.000Z",
      "effects": {
        "lightsaber": false,
        "glitch": true,
        "reasons": [
          "score≥2.1"
        ],
        "style": "glitch"
      },
      "category": "Sports",
      "region": "Canada"
    },
    {
      "title": "Ben Askren Emotional Over Life-Changing Year, 2026 Will 'Look Different'",
      "url": "https://www.tmz.com/2026/01/01/ben-askren-health-update-plans-for-new-year",
      "source": "TMZ.com",
      "published_utc": "2026-01-01T08:30:04.000Z",
      "effects": {
        "lightsaber": false,
        "glitch": false,
        "reasons": []
      },
      "category": "General",
      "region": "World"
    },
    {
      "title": "The world is still failing its children. We can change that in 2026",
      "url": "https://www.aljazeera.com/opinions/2026/1/1/the-world-is-still-failing-its-children-we-can-change-that-in?traffic_source=rss",
      "source": "Al Jazeera – Breaking News, World News and Video from Al Jazeera",
      "published_utc": "2026-01-01T08:21:31.000Z",
      "effects": {
        "lightsaber": false,
        "glitch": false,
        "reasons": []
      },
      "category": "General",
      "region": "World"
    },
    {
      "title": "Watch: Historic Amsterdam church engulfed by fire on New Year's Eve",
      "url": "https://www.bbc.com/news/videos/ckgkn1xexnno?at_campaign=rss&at_medium=RSS",
      "source": "BBC News",
      "published_utc": "2026-01-01T08:15:21.000Z",
      "effects": {
        "lightsaber": false,
        "glitch": false,
        "reasons": []
      },
      "category": "General",
      "region": "World"
    },
    {
      "title": "Why are some African countries banning US citizens from entry?",
      "url": "https://www.aljazeera.com/news/2026/1/1/why-are-some-african-countries-banning-us-citizens-from-entry?traffic_source=rss",
      "source": "Al Jazeera – Breaking News, World News and Video from Al Jazeera",
      "published_utc": "2026-01-01T08:10:49.000Z",
      "effects": {
        "lightsaber": false,
        "glitch": false,
        "reasons": []
      },
      "category": "General",
      "region": "World"
    },
    {
      "title": "Here are your 10 favourite photo stories of 2025",
      "url": "https://www.dazeddigital.com/art-photography/article/69354/1/10-best-photo-stories-2025-hujar-nan-goldin-juergen-teller-yorgos-feng-li",
      "source": "Dazed",
      "published_utc": "2026-01-01T08:10:00.000Z",
      "effects": {
        "lightsaber": false,
        "glitch": false,
        "reasons": []
      },
      "category": "Culture",
      "region": "World"
    },
    {
      "title": "Guess Who This Kid In Overalls Turned Into!",
      "url": "https://www.tmz.com/2026/01/01/guess-who-overalls-kid-turned-into",
      "source": "TMZ.com",
      "published_utc": "2026-01-01T08:01:34.000Z",
      "effects": {
        "lightsaber": false,
        "glitch": true,
        "reasons": [
          "score≥2.1"
        ],
        "style": "glitch"
      },
      "category": "General",
      "region": "Canada"
    },
    {
      "title": "“Stranger Things” Finale Crashes Netflix, Spectacular Ending After 9 Years, 5 Seasons, Wraps Story with Blazing Production",
      "url": "https://www.showbiz411.com/2026/01/01/stranger-things-finale-crashes-netflix-spectacular-ending-after-9-years-5-seasons-wraps-story-with-blazing-production",
      "source": "Showbiz411",
      "published_utc": "2026-01-01T08:01:29.000Z",
      "effects": {
        "lightsaber": false,
        "glitch": false,
        "reasons": []
      },
      "category": "General",
      "region": "World"
    },
    {
      "title": "Eat Better In 2026 with These Handy, Healthy Cookbooks",
      "url": "https://www.tmz.com/2026/01/01/healthy-cookbooks-2026-recipes",
      "source": "TMZ.com",
      "published_utc": "2026-01-01T08:01:14.000Z",
      "effects": {
        "lightsaber": false,
        "glitch": false,
        "reasons": []
      },
      "category": "General",
      "region": "World"
    },
    {
      "title": "Open Thread",
      "url": "https://reason.com/volokh/2026/01/01/open-thread-67",
      "source": "Reason.com",
      "published_utc": "2026-01-01T08:00:00.000Z",
      "effects": {
        "lightsaber": false,
        "glitch": false,
        "reasons": []
      },
      "category": "General",
      "region": "World"
    },
    {
      "title": "Israel escalates West Bank demolitions amid illegal settlement expansion",
      "url": "https://www.aljazeera.com/news/2026/1/1/israel-escalates-west-bank-demolitions-amid-illegal-settlement-expansion?traffic_source=rss",
      "source": "Al Jazeera – Breaking News, World News and Video from Al Jazeera",
      "published_utc": "2026-01-01T07:46:31.000Z",
      "effects": {
        "lightsaber": false,
        "glitch": false,
        "reasons": []
      },
      "category": "General",
      "region": "World"
    },
    {
      "title": "Watch Mariah Carey, Huntr/X and Post Malone bring in 2026 on ‘New Year’s Rockin’ Eve’ show in New York",
      "url": "https://www.nme.com/news/music/watch-mariah-carey-huntr-x-and-post-malone-bring-in-2026-on-new-years-rockin-eve-show-in-new-york-3920564",
      "source": "NME",
      "published_utc": "2026-01-01T07:45:28.000Z",
      "effects": {
        "lightsaber": false,
        "glitch": false,
        "reasons": []
      },
      "category": "Culture",
      "region": "World"
    },
    {
      "title": "Gaza’s new year begins with a struggle for survival and dignity",
      "url": "https://www.aljazeera.com/features/2026/1/1/gazas-new-year-begins-with-a-struggle-for-survival-and-dignity?traffic_source=rss",
      "source": "Al Jazeera – Breaking News, World News and Video from Al Jazeera",
      "published_utc": "2026-01-01T07:31:44.000Z",
      "effects": {
        "lightsaber": false,
        "glitch": false,
        "reasons": []
      },
      "category": "General",
      "region": "World"
    },
    {
      "title": "Palestine was the deadliest place to be a journalist in 2025: Media union",
      "url": "https://www.aljazeera.com/news/2026/1/1/palestine-was-the-deadliest-place-to-be-a-journalist-in-2025-media-union?traffic_source=rss",
      "source": "Al Jazeera – Breaking News, World News and Video from Al Jazeera",
      "published_utc": "2026-01-01T07:29:58.000Z",
      "effects": {
        "lightsaber": false,
        "glitch": false,
        "reasons": []
      },
      "category": "General",
      "region": "World"
    },
    {
      "title": "Andy Cohen Sends Eric Adams Off Into The Sunset With Drunken New Year’s Rant",
      "url": "https://dailycaller.com/2026/01/01/andy-cohen-eric-adams-new-years-eve-rant-cnn",
      "source": "The Daily Caller",
      "published_utc": "2026-01-01T07:03:04.000Z",
      "effects": {
        "lightsaber": false,
        "glitch": false,
        "reasons": []
      },
      "category": "General",
      "region": "World"
    },
    {
      "title": "Zohran Mamdani sworn in as New York City’s mayor",
      "url": "https://www.aljazeera.com/video/newsfeed/2026/1/1/zohran-mamdani-sworn-in-as-new-york-citys-mayor?traffic_source=rss",
      "source": "Al Jazeera – Breaking News, World News and Video from Al Jazeera",
      "published_utc": "2026-01-01T07:13:40.000Z",
      "effects": {
        "lightsaber": false,
        "glitch": false,
        "reasons": []
      },
      "category": "General",
      "region": "World"
    },
    {
      "title": "Photos: Zohran Mamdani becomes New York City’s first Muslim mayor",
      "url": "https://www.aljazeera.com/gallery/2026/1/1/photos-zohran-mamdani-becomes-new-york-citys-first-muslim-mayor?traffic_source=rss",
      "source": "Al Jazeera – Breaking News, World News and Video from Al Jazeera",
      "published_utc": "2026-01-01T06:54:33.000Z",
      "effects": {
        "lightsaber": false,
        "glitch": false,
        "reasons": []
      },
      "category": "General",
      "region": "World"
    },
    {
      "title": "Zohran Mamdani sworn in as first Muslim New York City Mayor",
      "url": "https://www.bbc.com/news/videos/c4glvg5yrlyo?at_campaign=rss&at_medium=RSS",
      "source": "BBC News",
      "published_utc": "2026-01-01T06:37:27.000Z",
      "effects": {
        "lightsaber": false,
        "glitch": false,
        "reasons": []
      },
      "category": "General",
      "region": "World"
    },
    {
      "title": "All the big elections to look out for in 2026",
      "url": "https://www.aljazeera.com/news/2026/1/1/all-the-big-elections-to-look-out-for-in-2026?traffic_source=rss",
      "source": "Al Jazeera – Breaking News, World News and Video from Al Jazeera",
      "published_utc": "2026-01-01T06:44:18.000Z",
      "effects": {
        "lightsaber": false,
        "glitch": false,
        "reasons": []
      },
      "category": "General",
      "region": "World"
    },
    {
      "title": "Several killed in blaze at Swiss ski resort town: Police",
      "url": "https://www.aljazeera.com/news/2026/1/1/several-killed-in-explosion-fire-at-swiss-ski-resort-town-police?traffic_source=rss",
      "source": "Al Jazeera – Breaking News, World News and Video from Al Jazeera",
      "published_utc": "2026-01-01T06:53:44.000Z",
      "effects": {
        "lightsaber": false,
        "glitch": false,
        "reasons": []
      },
      "category": "General",
      "region": "World"
    },
    {
      "title": "Final nail in the 4-year cycle? BTC ends year after halving in the red",
      "url": "https://cointelegraph.com/news/is-bitcoin-four-year-cycle-dead-2025",
      "source": "Cointelegraph.com News",
      "published_utc": "2026-01-01T06:30:06.000Z",
      "effects": {
        "lightsaber": false,
        "glitch": false,
        "reasons": []
      },
      "category": "Business",
      "region": "World"
    },
    {
      "title": "Stranger Things Ends with a Whimper",
      "url": "https://consequence.net/2026/01/stranger-things-series-finale-recap-review",
      "source": "Consequence",
      "published_utc": "2026-01-01T06:25:58.000Z",
      "effects": {
        "lightsaber": false,
        "glitch": false,
        "reasons": []
      },
      "category": "Labour",
      "region": "World"
    },
    {
      "title": "Investors funnel $32B into US crypto ETFs despite year-end pullback",
      "url": "https://cointelegraph.com/news/us-spot-crypto-etfs-see-32-billion-inflows-2025",
      "source": "Cointelegraph.com News",
      "published_utc": "2026-01-01T06:25:53.000Z",
      "effects": {
        "lightsaber": false,
        "glitch": false,
        "reasons": []
      },
      "category": "Business",
      "region": "World"
    },
    {
      "title": "5 Times Liberal Pundits Admitted Painfully Obvious Truths In 2025",
      "url": "https://dailycaller.com/2026/01/01/5-times-prominent-media-pundits-admitted-obvious-truths-2025",
      "source": "The Daily Caller",
      "published_utc": "2026-01-01T06:19:57.000Z",
      "effects": {
        "lightsaber": false,
        "glitch": false,
        "reasons": []
      },
      "category": "General",
      "region": "World"
    },
    {
      "title": "NewJeans member Danielle sued for millions after bitter feud with K-pop record label",
      "url": "https://www.theguardian.com/music/2026/jan/01/newjeans-member-danielle-sued-for-millions-after-bitter-feud-with-k-pop-record-label",
      "source": "World news | The Guardian",
      "published_utc": "2026-01-01T06:19:14.000Z",
      "effects": {
        "lightsaber": false,
        "glitch": false,
        "reasons": []
      },
      "category": "General",
      "region": "World"
    },
    {
      "title": "8 Times Liberals Literally Cried In 2025",
      "url": "https://dailycaller.com/2026/01/01/8-times-liberals-cried-2025",
      "source": "The Daily Caller",
      "published_utc": "2026-01-01T06:19:11.000Z",
      "effects": {
        "lightsaber": false,
        "glitch": false,
        "reasons": []
      },
      "category": "General",
      "region": "World"
    },
    {
      "title": "10 Times Democrats, Corporate Media Leaped To Defend Somalis Despite Massive Fraud Scandals",
      "url": "https://dailycaller.com/2026/01/01/10-times-democrats-corporate-media-leaped-to-defend-somalis-despite-massive-fraud-scandals",
      "source": "The Daily Caller",
      "published_utc": "2026-01-01T06:18:09.000Z",
      "effects": {
        "lightsaber": false,
        "glitch": false,
        "reasons": []
      },
      "category": "General",
      "region": "World"
    },
    {
      "title": "‘See You at Zero Bond!’ Anderson Cooper Tries (And Fails) to Stop Andy Cohen’s Wild Riff On Eric Adams",
      "url": "https://www.mediaite.com/media/see-you-at-zero-bond-anderson-cooper-tries-and-fails-to-stop-andy-cohens-wild-riff-on-eric-adams",
      "source": "Mediaite",
      "published_utc": "2026-01-01T05:58:37.000Z",
      "effects": {
        "lightsaber": false,
        "glitch": false,
        "reasons": []
      },
      "category": "General",
      "region": "World"
    },
    {
      "title": "Zohran Mamdani sworn in as New York City mayor, capping historic rise",
      "url": "https://www.npr.org/2026/01/01/nx-s1-5663372/zohran-mamdani-sworn-in-as-new-york-city-mayor-capping-historic-rise",
      "source": "NPR Topics: Home Page Top Stories",
      "published_utc": "2026-01-01T05:58:09.000Z",
      "effects": {
        "lightsaber": false,
        "glitch": false,
        "reasons": []
      },
      "category": "General",
      "region": "World"
    },
    {
      "title": "4 crypto comebacks from 2025 that could help shape the year ahead",
      "url": "https://cointelegraph.com/news/4-crypto-comebacks-2025-shaping-the-next-year",
      "source": "Cointelegraph.com News",
      "published_utc": "2026-01-01T05:57:58.000Z",
      "effects": {
        "lightsaber": false,
        "glitch": false,
        "reasons": []
      },
      "category": "Business",
      "region": "World"
    },
    {
      "title": "BTS to Return in March With First Album in Nearly Four Years",
      "url": "https://variety.com/2025/music/news/bts-new-album-coming-march-1236621674",
      "source": "Variety",
      "published_utc": "2026-01-01T05:56:13.000Z",
      "effects": {
        "lightsaber": false,
        "glitch": false,
        "reasons": []
      },
      "category": "General",
      "region": "World"
    },
    {
      "title": "Chappell Roan Welcomes the New Year With Dreamy Performance of ‘The Subway’ on ‘Rockin’ Eve’",
      "url": "https://www.rollingstone.com/music/music-news/chappell-roan-performance-new-years-rockin-eve-1235491659",
      "source": "Rolling Stone",
      "published_utc": "2026-01-01T05:52:15.000Z",
      "effects": {
        "lightsaber": false,
        "glitch": false,
        "reasons": []
      },
      "category": "General",
      "region": "World"
    },
    {
      "title": "CBS’ ‘New Year’s Eve Live: Nashville’s Big Bash’ Special Faces Mid-Show Outage",
      "url": "https://variety.com/2025/tv/news/cbs-nashvilles-big-bash-live-technical-problem-matlock-1236621691",
      "source": "Variety",
      "published_utc": "2026-01-01T05:51:53.000Z",
      "effects": {
        "lightsaber": false,
        "glitch": false,
        "reasons": []
      },
      "category": "General",
      "region": "World"
    },
    {
      "title": "Miami stuns defending champ Ohio State to advance to CFP semis",
      "url": "https://nypost.com/2026/01/01/sports/miami-stuns-defending-champ-ohio-state-to-advance-to-cfp-semis",
      "source": "NY Post Sports – Latest News, Scores, Stats & Videos",
      "published_utc": "2026-01-01T05:49:26.000Z",
      "effects": {
        "lightsaber": false,
        "glitch": true,
        "reasons": [
          "score≥2.1"
        ],
        "style": "glitch"
      },
      "category": "Sports",
      "region": "Canada"
    },
    {
      "title": "‘Stranger Things 5’ Finale Review: Duffer Brothers Achieve the Impossible With Epic Ending",
      "url": "https://www.thewrap.com/creative-content/tv-shows/stranger-things-season-5-finale-review",
      "source": "TheWrap",
      "published_utc": "2026-01-01T05:40:00.000Z",
      "effects": {
        "lightsaber": false,
        "glitch": false,
        "reasons": []
      },
      "category": "General",
      "region": "World"
    },
    {
      "title": "Each Team’s Free Agent Activity So Far",
      "url": "https://www.mlbtraderumors.com/2025/12/each-teams-free-agent-activity-so-far.html",
      "source": "MLB Trade Rumors",
      "published_utc": "2026-01-01T05:36:28.000Z",
      "effects": {
        "lightsaber": true,
        "glitch": false,
        "reasons": [
          "score≥2.6"
        ],
        "style": "lightsaber"
      },
      "category": "Sports",
      "region": "Canada"
    },
    {
      "title": "Kona Takahashi’s Posting Window Nearing Conclusion",
      "url": "https://www.mlbtraderumors.com/2025/12/kona-takahashis-posting-window-nearing-conclusion.html",
      "source": "MLB Trade Rumors",
      "published_utc": "2026-01-01T05:31:32.000Z",
      "effects": {
        "lightsaber": true,
        "glitch": false,
        "reasons": [
          "score≥2.6"
        ],
        "style": "lightsaber"
      },
      "category": "Sports",
      "region": "Canada"
    },
    {
      "title": "Zohran Mamdani takes oath as New York mayor with historic Quran",
      "url": "https://www.aljazeera.com/news/2026/1/1/zohran-mamdani-sworn-in-as-new-york-mayor-with-historic-quran?traffic_source=rss",
      "source": "Al Jazeera – Breaking News, World News and Video from Al Jazeera",
      "published_utc": "2026-01-01T05:31:11.000Z",
      "effects": {
        "lightsaber": false,
        "glitch": false,
        "reasons": []
      },
      "category": "General",
      "region": "World"
    },
    {
      "title": "Pastrnak, Bruins cruise past Oilers 6-2",
      "url": "https://globalnews.ca/news/11596099/pastrnak-bruins-cruise-past-oilers-6-2",
      "source": "globalnews.ca",
      "published_utc": "2026-01-01T05:27:15.000Z",
      "effects": {
        "lightsaber": true,
        "glitch": false,
        "reasons": [
          "score≥2.6"
        ],
        "style": "lightsaber"
      },
      "category": "General",
      "region": "Canada"
    },
    {
      "title": "Zelensky says peace deal is 90% ready in New Year address",
      "url": "https://www.bbc.com/news/articles/cddg7100ym2o?at_campaign=rss&at_medium=RSS",
      "source": "BBC News",
      "published_utc": "2026-01-01T05:22:01.000Z",
      "effects": {
        "lightsaber": false,
        "glitch": false,
        "reasons": []
      },
      "category": "General",
      "region": "World"
    },
    {
      "title": "Anderson Cooper Sheepishly Punts When Andy Cohen Asks if He’d Rather Give Up ‘Cheeseburgers’ Or ‘Oral Sex’",
      "url": "https://www.mediaite.com/media/anderson-cooper-sheepishly-punts-when-andy-cohen-asks-if-hed-rather-give-up-cheeseburgers-or-oral-sex",
      "source": "Mediaite",
      "published_utc": "2026-01-01T05:19:06.000Z",
      "effects": {
        "lightsaber": false,
        "glitch": false,
        "reasons": []
      },
      "category": "General",
      "region": "World"
    },
    {
      "title": "Knicks blow late double-digit lead to Spurs to end 2025 on sour note",
      "url": "https://nypost.com/2026/01/01/sports/knicks-blow-late-double-digit-lead-to-spurs-to-end-2025-on-sour-note",
      "source": "NY Post Sports – Latest News, Scores, Stats & Videos",
      "published_utc": "2026-01-01T05:02:23.000Z",
      "effects": {
        "lightsaber": false,
        "glitch": false,
        "reasons": []
      },
      "category": "Sports",
      "region": "Canada"
    },
    {
      "title": "Andy Cohen Reveals He ‘Black Lighted’ His Bed Before Gifting It to CNN Pal Anderson Cooper",
      "url": "https://www.mediaite.com/media/andy-cohen-reveals-he-black-lighted-his-bed-before-gifting-it-to-cnn-pal-anderson-cooper",
      "source": "Mediaite",
      "published_utc": "2026-01-01T05:02:21.000Z",
      "effects": {
        "lightsaber": false,
        "glitch": false,
        "reasons": []
      },
      "category": "General",
      "region": "World"
    },
    {
      "title": "Rising from the ashes, a symbol of hope at the Rose Parade",
      "url": "https://www.npr.org/2026/01/01/nx-s1-5653371/rose-parade-phoenix-float-los-angeles-fires",
      "source": "NPR Topics: Home Page Top Stories",
      "published_utc": "2026-01-01T05:01:00.000Z",
      "effects": {
        "lightsaber": false,
        "glitch": false,
        "reasons": []
      },
      "category": "General",
      "region": "World"
    },
    {
      "title": "‘KPop Demon Hunters’ Singers Deliver ‘Golden’ Performance at ‘New Year’s Rockin’ Eve’",
      "url": "https://www.rollingstone.com/music/music-news/kpop-demon-hunters-huntrx-perform-golden-new-years-eve-1235492310",
      "source": "Rolling Stone",
      "published_utc": "2026-01-01T05:00:03.000Z",
      "effects": {
        "lightsaber": false,
        "glitch": false,
        "reasons": []
      },
      "category": "General",
      "region": "World"
    },
    {
      "title": "Crypto forces to compound in 2026, accelerating adoption: Coinbase",
      "url": "https://cointelegraph.com/news/crypto-forces-compound-2026-adoption",
      "source": "Cointelegraph.com News",
      "published_utc": "2026-01-01T04:58:31.000Z",
      "effects": {
        "lightsaber": false,
        "glitch": false,
        "reasons": []
      },
      "category": "Business",
      "region": "World"
    },
    {
      "title": "Suspect charged in connection with 2 sexual assaults, 2 assaults, break-and-enter: Toronto police",
      "url": "https://toronto.citynews.ca/2025/12/31/suspect-charged-in-connection-with-2-sexual-assaults-2-assaults-break-and-enter-toronto-police",
      "source": "CityNews Toronto",
      "published_utc": "2026-01-01T04:43:27.000Z",
      "effects": {
        "lightsaber": true,
        "glitch": false,
        "reasons": [
          "score≥2.6"
        ],
        "style": "lightsaber"
      },
      "category": "Local",
      "region": "Canada"
    },
    {
      "title": "MEHEK COOKE: Hey Dems, What Happened To ‘Trust The Intel Community’?",
      "url": "https://dailycaller.com/2025/12/31/opinion-hey-dems-what-happened-to-trust-the-intel-community-mehek-cooke",
      "source": "The Daily Caller",
      "published_utc": "2026-01-01T04:39:14.000Z",
      "effects": {
        "lightsaber": false,
        "glitch": false,
        "reasons": []
      },
      "category": "General",
      "region": "World"
    },
    {
      "title": "Andy Cohen and Anderson Cooper Struggle to Operate Large Puppets During NYE Show: We’re ‘Transitioning… Into Drunkards!’",
      "url": "https://www.mediaite.com/media/tv/andy-cohen-and-anderson-cooper-struggle-to-operate-large-puppets-during-nye-show-were-transitioning-into-drunkards",
      "source": "Mediaite",
      "published_utc": "2026-01-01T04:37:21.000Z",
      "effects": {
        "lightsaber": false,
        "glitch": false,
        "reasons": []
      },
      "category": "General",
      "region": "World"
    }
  ],
  "_debug": {
    "feeds_total": 154,
    "cap_items": 320,
    "collected": 800,
    "dedup_pass1": 783,
    "dedup_final": 320,
    "slow_domains": [],
    "timeouts": [
      "japantoday.com",
      "news.communitech.ca",
      "www.cbc.ca"
    ],
    "errors": [
      "alert.weather.gc.ca",
      "feeds.reuters.com"
    ],
    "caps_hit": [
      "cultmtl.com",
      "financialpost.com",
      "nypost.com",
      "toronto.citynews.ca",
      "variety.com",
      "www.boston.com",
      "www.marketwatch.com",
      "www.npr.org",
      "www.wsj.com"
    ],
    "feed_times_sample": [
      {
        "host": "www.labourstart.org",
        "sec": 1.854,
        "kept": 0
      },
      {
        "host": "toronto.citynews.ca",
        "sec": 1.013,
        "kept": 8
      },
      {
        "host": "globalnews.ca",
        "sec": 0.873,
        "kept": 1
      },
      {
        "host": "www.mlb.com",
        "sec": 0.652,
        "kept": 14
      },
      {
        "host": "www.blogto.com",
        "sec": 0.587,
        "kept": 0
      },
      {
        "host": "www.cp24.com",
        "sec": 0.547,
        "kept": 14
      },
      {
        "host": "www.bls.gov",
        "sec": 0.368,
        "kept": 0
      },
      {
        "host": "www.mlbtraderumors.com",
        "sec": 0.346,
        "kept": 14
      },
      {
        "host": "www.federalreserve.gov",
        "sec": 0.183,
        "kept": 14
      },
      {
        "host": "www.nhl.com",
        "sec": 0.173,
        "kept": 0
      }
    ],
    "elapsed_sec": 338.26,
    "http_timeout_sec": 10,
    "slow_feed_warn_sec": 3.5,
    "global_budget_sec": 210,
    "version": "fetch-v2.7.0-obits-am-bias",
    "weights_loaded": true,
    "weights_keys": [
      "categories",
      "daypart",
      "effects",
      "labour_keywords",
      "markets",
      "public_safety",
      "recency",
      "regional",
      "reorder",
      "salience",
      "sources",
      "sports",
      "timezone"
    ],
    "weights_error": "",
    "weights_path": "config/weights.json5",
    "score_stats": {
      "effects_lightsaber": 0,
      "effects_glitch": 0,
      "ps_fatal_hits": 24,
      "ps_injury_hits": 1,
      "market_btc_hits": 1,
      "market_index_hits": 0,
      "market_nikkei_hits": 0,
      "market_single_hits": 0,
      "agg_penalties": 0,
      "press_penalties": 0,
      "preferred_bonus": 123,
      "substack_tagged": 0,
      "sports_team_hits": 6,
      "sports_player_hits": 1,
      "sports_result_win_hits": 15,
      "sports_result_loss_hits": 0,
      "sports_evening_hits": 0,
      "sports_playoff_hits": 0,
      "sports_focus_team_hits": 7,
      "sports_final_hits": 0,
      "sports_final_score_hits": 0,
      "hype_politics": 0,
      "hype_conflict": 0,
      "hype_markets": 0,
      "hype_jobs": 0,
      "hype_sports": 0,
      "hype_ceasefire": 0,
      "reject_hits": 0,
      "obit_hits": 9,
      "major_figure_hits": 2,
      "business_am_hits": 0
    },
    "sanity_stats": {
      "link_verification_fail": 20,
      "soft_404_drops": 46,
      "max_age_drops": 0,
      "min_age_drops": 0,
      "market_sanity_drops": 3,
      "backfill_steps_used": 0
    },
    "require_exact_count": 69,
    "age_window_hours": 69,
    "min_age_sec": 60,
    "verify_links": true,
    "reject_homepage_redirect": true,
    "block_aggregators": true,
    "fallback": {
      "used": false,
      "feed": null,
      "title": null,
      "feeds_considered": [
        "https://www.reuters.com/world/us/rss",
        "https://www.reuters.com/world/rss",
        "https://www.cbc.ca/cmlink/rss-topstories",
        "https://www.ctvnews.ca/rss/ctvnews-ca-top-stories-public-rss-1.822009",
        "https://globalnews.ca/feed/",
        "https://www.cp24.com"
      ],
      "max_age_hours": 24,
      "min_items": 1
    }
  }
}
